NewsExtractor/__init__.py
NewsExtractor/defaults.py
NewsExtractor/utils.py
NewsExtractor/extractor/AuthorExtractor.py
NewsExtractor/extractor/ContentExtractor.py
NewsExtractor/extractor/TimeExtractor.py
NewsExtractor/extractor/TitleExtractor.py
NewsExtractor/extractor/__init__.py
NewsExtractor-1.0.dist-info/LICENSE
NewsExtractor-1.0.dist-info/METADATA
NewsExtractor-1.0.dist-info/WHEEL
NewsExtractor-1.0.dist-info/top_level.txt
NewsExtractor-1.0.dist-info/RECORD
